[
  {
    "title": "일본 소년 H와 한국 BTS",
    "link": "https://www.mindlenews.com/news/articleView.html?idxno=20419",
    "pubDate": "Sun, 24 May 2026 01:00:00 GMT",
    "source": "세상을 바꾸는 시민언론 민들레",
    "domain": "mindlenews.com",
    "thumb": "https://cdn.mindlenews.com/news/thumbnail/202605/20419_69448_3057_v150.jpg"
  },
  {
    "title": "빅히트 뮤직, BTS·TXT·CORTIS 삼각편대로 ‘글로벌 톱 레이블’ 입증",
    "link": "https://sports.khan.co.kr/article/202605240742003",
    "pubDate": "Sat, 23 May 2026 22:42:00 GMT",
    "source": "스포츠경향",
    "domain": "sports.khan.co.kr",
    "thumb": null
  },
  {
    "title": "BTS 슈가, 무대 위 카리스마-일상 모습 '반전 매력' 포착",
    "link": "https://www.ppss.kr/news/articleView.html?idxno=296941",
    "pubDate": "Sat, 23 May 2026 22:08:06 GMT",
    "source": "ppss.kr",
    "domain": "ppss.kr",
    "thumb": "https://cdn.ppss.kr/news/photo/202605/296941_114642_640.jpg"
  },
  {
    "title": "방탄소년단, 5년 만에 '아메리칸 뮤직 어워즈' 대상 받을까",
    "link": "https://www.newsis.com/view/NISX20260524_0003642194",
    "pubDate": "Sat, 23 May 2026 21:10:34 GMT",
    "source": "뉴시스",
    "domain": "newsis.com",
    "thumb": "https://img1.newsis.com/2026/05/09/NISI20260509_0002131041_web.jpg"
  },
  {
    "title": "\"다시 오지 않을 부산 될 수도\"…BTS '숙박 폭등'에 시민단체 \"적극 나서야\"",
    "link": "https://www.news1.kr/local/busan-gyeongnam/6175622",
    "pubDate": "Sat, 23 May 2026 21:00:00 GMT",
    "source": "뉴스1",
    "domain": "news1.kr",
    "thumb": "https://i3n.news1.kr/system/photos/2026/4/9/7847004/high.jpg"
  },
  {
    "title": "방탄소년단 뷔, 엠버서더 활동 중인 브랜드에 경사",
    "link": "https://theviewers.co.kr/View.aspx?No=4087044",
    "pubDate": "Sat, 23 May 2026 12:07:41 GMT",
    "source": "뷰어스",
    "domain": "theviewers.co.kr",
    "thumb": "https://cdn.coenworks.com/Files/30/News/202605/2890_20260522014009658.jpg"
  },
  {
    "title": "BTS 품은 디스트릭트…'아르떼' 글로벌 베팅 승부수",
    "link": "https://news.nate.com/view/20260523n08590",
    "pubDate": "Sat, 23 May 2026 06:01:00 GMT",
    "source": "네이트",
    "domain": "news.nate.com",
    "thumb": "https://thumbnews.nateimg.co.kr/view610///news.nateimg.co.kr/orgImg/bt/2026/05/23/663241_275756_2613.jpg"
  },
  {
    "title": "빅히트 뮤직, BTS·TXT·CORTIS ‘릴레이 메가 히트’",
    "link": "https://enews.imbc.com/News/RetrieveNewsInfo/505911",
    "pubDate": "Sat, 23 May 2026 03:04:00 GMT",
    "source": "iMBC 연예",
    "domain": "enews.imbc.com",
    "thumb": "https://talkimg.imbc.com/TVianUpload/tvian/TViews/image/2026/05/23/d4859aa3-d086-4e86-a727-d048b548c486.jpg"
  },
  {
    "title": "BTS·TXT·코르티스 삼각편대..빅히트 뮤직, ‘글로벌 톱 레이블’ 이름값 증명",
    "link": "https://www.chosun.com/entertainments/music/2026/05/23/MNSGKMDCMRTDOMRRHFQTMMJTMM/",
    "pubDate": "Sat, 23 May 2026 02:20:00 GMT",
    "source": "조선일보",
    "domain": "chosun.com",
    "thumb": "https://www.chosun.com/resizer/v2/GFSTENTDGRRWGMZWGFRDMOBXG4.jpg?auth=aa25439a9c65d8f4e3b219d16ccf030aad7e114d8d2c77240808e7b7731dbc10&amp;width=650&amp;height=341&amp;smart=true"
  },
  {
    "title": "뷔 한 마디에 또…BTS 다녀간 美 피자집, 14년 만 역대급 난리",
    "link": "https://www.mk.co.kr/news/world/12056157",
    "pubDate": "Sat, 23 May 2026 01:00:48 GMT",
    "source": "매일경제",
    "domain": "mk.co.kr",
    "thumb": "https://pimg.mk.co.kr/news/cms/202605/23/news-p.v1.20260523.ed75db28fd624a70946f6b4e275289df_R.jpg"
  },
  {
    "title": "BTS '아리랑', 스포티파이 주간 앨범 차트 9주 연속 '톱 3'",
    "link": "https://www.news1.kr/entertain/music/6175892",
    "pubDate": "Sat, 23 May 2026 00:37:59 GMT",
    "source": "뉴스1",
    "domain": "news1.kr",
    "thumb": "https://i3n.news1.kr/system/photos/2026/5/23/7922059/high.jpg"
  },
  {
    "title": "BTS '아리랑', 스포티파이 주간 앨범 차트 이번 주에도 '글로벌 2위'",
    "link": "https://v.daum.net/v/20260523080649906",
    "pubDate": "Fri, 22 May 2026 23:06:49 GMT",
    "source": "v.daum.net",
    "domain": "v.daum.net",
    "thumb": "https://img1.daumcdn.net/thumb/S1200x630/?fname=https://t1.daumcdn.net/news/202605/23/mydaily/20260523080651123yzji.jpg"
  },
  {
    "title": "방탄소년단 '스윔', 英 싱글차트 9주 연속 톱60…마이클 잭슨 열풍 계속",
    "link": "https://www.newsis.com/view/NISX20260523_0003641789",
    "pubDate": "Fri, 22 May 2026 22:45:07 GMT",
    "source": "뉴시스",
    "domain": "newsis.com",
    "thumb": "https://img1.newsis.com/2026/05/02/NISI20260502_0002126000_web.jpg"
  },
  {
    "title": "BTS 뷔 “스탠퍼드 피자 최고”…한마디에 美 식당, 한마디로 대박",
    "link": "https://v.daum.net/v/7KN5k5lwuJ",
    "pubDate": "Fri, 22 May 2026 22:19:08 GMT",
    "source": "v.daum.net",
    "domain": "v.daum.net",
    "thumb": "https://img1.daumcdn.net/thumb/S1200x630/?fname=https://t1.daumcdn.net/news/202605/23/sportsdonga/20260523071910342pdtn.jpg"
  },
  {
    "title": "“10대 아미, 20년 뒤 韓 GDP 높인다”…‘방탄노믹스 효과’ 깜짝",
    "link": "https://v.daum.net/v/20260523070316208",
    "pubDate": "Fri, 22 May 2026 22:03:16 GMT",
    "source": "v.daum.net",
    "domain": "v.daum.net",
    "thumb": "https://img1.daumcdn.net/thumb/S1200x630/?fname=https://t1.daumcdn.net/news/202605/23/joongang/20260523070316507druw.jpg"
  },
  {
    "title": "\"바가지 막겠다\"던 부산시…BTS 숙박 요금 폭등 여전, 왜?",
    "link": "https://www.news1.kr/local/busan-gyeongnam/6175513",
    "pubDate": "Fri, 22 May 2026 21:00:00 GMT",
    "source": "뉴스1",
    "domain": "news1.kr",
    "thumb": "https://i3n.news1.kr/system/photos/2026/5/22/7921545/high.jpg"
  },
  {
    "title": "11년 전 BTS가 나선 골프장 콘서트… 지역 상생 모델 됐다",
    "link": "https://v.daum.net/v/BlawBB1ySJ",
    "pubDate": "Fri, 22 May 2026 15:14:18 GMT",
    "source": "v.daum.net",
    "domain": "v.daum.net",
    "thumb": "https://img1.daumcdn.net/thumb/S1200x630/?fname=https://t1.daumcdn.net/news/202605/23/kukminilbo/20260523001419504xvcv.jpg"
  },
  {
    "title": "LIV골프대회에 BTS 투어...부산 '빅이벤트' 잇따르지만...",
    "link": "https://news.knn.co.kr/news/article/188103",
    "pubDate": "Fri, 22 May 2026 11:10:00 GMT",
    "source": "knn.co.kr",
    "domain": "news.knn.co.kr",
    "thumb": "https://kcms.knn.co.kr/mam/data/CI2016123000000000006/CI2017072513315301673/2026/05/22/26052254398/catalog/6.jpg"
  },
  {
    "title": "BTS 공연 숙박난에 부산경남 사찰 숙소 지원나서",
    "link": "https://news.knn.co.kr/news/article/188099",
    "pubDate": "Fri, 22 May 2026 11:10:00 GMT",
    "source": "knn.co.kr",
    "domain": "news.knn.co.kr",
    "thumb": "https://kcms.knn.co.kr/mam/data/CI2016123000000000006/CI2017072513315301673/2026/05/22/26052254395/26052254395.jpg"
  },
  {
    "title": "단속 비웃는 ‘BTS 특수’ 숙박료 10배 폭등… 법 개정 미비에 부산시 ‘속수무책’",
    "link": "https://v.daum.net/v/20260522185411478",
    "pubDate": "Fri, 22 May 2026 09:54:11 GMT",
    "source": "v.daum.net",
    "domain": "v.daum.net",
    "thumb": "https://img1.daumcdn.net/thumb/S1200x630/?fname=https://t1.daumcdn.net/news/202605/22/551750-8jup1yA/20260522185413088tehl.jpg"
  },
  {
    "title": "BTS, 美스탠퍼드 공연에 15만 명…‘아리랑’ 떼창에 태극기로 물들어",
    "link": "https://v.daum.net/v/20260522170617334",
    "pubDate": "Fri, 22 May 2026 08:06:17 GMT",
    "source": "v.daum.net",
    "domain": "v.daum.net",
    "thumb": "https://img1.daumcdn.net/thumb/S1200x630/?fname=https://t1.daumcdn.net/news/202605/22/kbs/20260522170717179hsmz.jpg"
  },
  {
    "title": "‘바가지 요금 NO' BTS 맞이하는 부산, 불교계 필두로 '공정숙박 챌린지' 확산",
    "link": "https://v.daum.net/v/20260522164043345",
    "pubDate": "Fri, 22 May 2026 07:40:43 GMT",
    "source": "v.daum.net",
    "domain": "v.daum.net",
    "thumb": "https://img1.daumcdn.net/thumb/S1200x630/?fname=https://t1.daumcdn.net/news/202605/22/551750-8jup1yA/20260522173702936tmat.jpg"
  },
  {
    "title": "BTS '숙박대란', 부산·경남 사찰이 품는다",
    "link": "https://www.hyunbulnews.com/news/articleView.html?idxno=503575",
    "pubDate": "Fri, 22 May 2026 07:35:23 GMT",
    "source": "현대불교",
    "domain": "hyunbulnews.com",
    "thumb": "https://cdn.hyunbulnews.com/news/photo/202605/503575_217257_3437.jpg"
  },
  {
    "title": "BTS 부산 월드투어에 범어사 등 외국인 관광객 무료 템플스테이",
    "link": "https://www.chosun.com/national/regional/2026/05/22/RY4ODSRJAFFPHB3LT7QXH2O5EE/",
    "pubDate": "Fri, 22 May 2026 07:05:04 GMT",
    "source": "조선일보",
    "domain": "chosun.com",
    "thumb": "https://www.chosun.com/resizer/v2/GPS52AQ4KNHZNH6HITASYBFPGE.JPG?auth=d2ae7819ccbc7dabc5c9915bee61065eb53362794a8aff9a6958f97fb27c2ceb&amp;width=1200&amp;height=630&amp;smart=true"
  },
  {
    "title": "BTS 부산 공연에…경남 숙박업소 “예약 알박기 피해”",
    "link": "https://v.daum.net/v/20260522155827654",
    "pubDate": "Fri, 22 May 2026 06:58:27 GMT",
    "source": "v.daum.net",
    "domain": "v.daum.net",
    "thumb": "https://img1.daumcdn.net/thumb/S1200x630/?fname=https://t1.daumcdn.net/news/202605/22/551753-slRgb6U/20260522155828800ayfs.jpg"
  },
  {
    "title": "BTS (방탄소년단) WORLD TOUR ‘ARIRANG’ I",
    "link": "https://weverse.io/bts/notice/36080?hl=ko",
    "pubDate": "Fri, 22 May 2026 06:22:45 GMT",
    "source": "Weverse",
    "domain": "weverse.io",
    "thumb": null
  },
  {
    "title": "\"BTS 빌보드 1위 세계관은\"…디스트릭트, 5개 미디어아트 협업",
    "link": "https://www.news1.kr/industry/sb-founded/6175403",
    "pubDate": "Fri, 22 May 2026 06:12:18 GMT",
    "source": "뉴스1",
    "domain": "news1.kr",
    "thumb": "https://i3n.news1.kr/system/photos/2026/5/22/7921249/high.jpg"
  },
  {
    "title": "'아리랑' 떼창에 태극기 물결…BTS, 美스탠퍼드 공연에 15만명",
    "link": "https://www.yna.co.kr/view/AKR20260522098000005",
    "pubDate": "Fri, 22 May 2026 05:42:41 GMT",
    "source": "연합뉴스",
    "domain": "yna.co.kr",
    "thumb": "https://img8.yna.co.kr/etc/inner/KR/2026/05/22/AKR20260522098000005_03_i_P4.jpg"
  },
  {
    "title": "BTS, 美 스탠퍼드 스타디움 태극기로 물들였다…15만 2천 관객 열광",
    "link": "https://www.news1.kr/entertain/music/6175285",
    "pubDate": "Fri, 22 May 2026 05:15:52 GMT",
    "source": "뉴스1",
    "domain": "news1.kr",
    "thumb": "https://i3n.news1.kr/system/photos/2026/5/22/7921095/high.jpg"
  },
  {
    "title": "라스베이거스, ‘보라해가스’됐다…BTS 맞이에 한창",
    "link": "https://biz.heraldcorp.com/article/10743561",
    "pubDate": "Fri, 22 May 2026 02:41:32 GMT",
    "source": "헤럴드경제",
    "domain": "biz.heraldcorp.com",
    "thumb": "https://wimg.heraldcorp.com/news/cms/2026/05/22/news-p.v1.20260522.65439f22643d4fa0b3b92ce0ff08777e_T1.jpg"
  },
  {
    "title": "'6만원 방이 300만원' BTS 부산 콘서트 앞 아우성…\"차라리 서울서 숙박\"",
    "link": "https://www.news1.kr/society/general-society/6174003",
    "pubDate": "Thu, 21 May 2026 19:00:00 GMT",
    "source": "뉴스1",
    "domain": "news1.kr",
    "thumb": "https://i3n.news1.kr/system/photos/2026/5/7/7893763/high.jpg"
  },
  {
    "title": "BTS 정국 노린 해킹 조직, 재벌가 돈 털려고 작전",
    "link": "https://imnews.imbc.com/replay/2026/nwdesk/article/6824401_37004.html",
    "pubDate": "Thu, 21 May 2026 11:32:35 GMT",
    "source": "MBC 뉴스",
    "domain": "imnews.imbc.com",
    "thumb": "https://image.imnews.imbc.com/replay/2026/nwdesk/article/__icsFiles/afieldfile/2026/05/21/desk_20260521_203107_1_22_Large.jpg"
  },
  {
    "title": "BTS “여기가 최고” 한마디에…美 피자집 미어터졌다",
    "link": "https://www.donga.com/news/Inter/article/all/20260521/133970544/2",
    "pubDate": "Thu, 21 May 2026 08:41:00 GMT",
    "source": "동아일보",
    "domain": "donga.com",
    "thumb": "https://dimg.donga.com/wps/NEWS/IMAGE/2026/05/21/133970538.3.jpg"
  },
  {
    "title": "BTS, 아메리칸 뮤직 어워드 시상식 출격…대상 수상 노린다",
    "link": "https://v.daum.net/v/20260521173218774",
    "pubDate": "Thu, 21 May 2026 08:32:18 GMT",
    "source": "v.daum.net",
    "domain": "v.daum.net",
    "thumb": "https://img1.daumcdn.net/thumb/S1200x630/?fname=https://t1.daumcdn.net/news/202605/21/joongang/20260521173219943znns.jpg"
  },
  {
    "title": "“불교계 눈물나게 고마워”···‘1박 90만원’ 부산 BTS 공연 바가지 숙박비에 절에서 팔 걷었다",
    "link": "https://www.khan.co.kr/article/202605211541001",
    "pubDate": "Thu, 21 May 2026 06:41:00 GMT",
    "source": "경향신문",
    "domain": "khan.co.kr",
    "thumb": "https://img.khan.co.kr/news/2026/05/21/news-p.v1.20260515.071a6706524841958b3b8129bec22ea1_P1.png"
  },
  {
    "title": "BTS 정국 노렸던 700억원대 해킹 조직 총책 내일 검찰 송치",
    "link": "https://v.daum.net/v/20260521142217950",
    "pubDate": "Thu, 21 May 2026 05:22:17 GMT",
    "source": "v.daum.net",
    "domain": "v.daum.net",
    "thumb": "https://img1.daumcdn.net/thumb/S1200x630/?fname=https://t1.daumcdn.net/news/202605/21/kado/20260521142219202kggr.jpg"
  },
  {
    "title": "BTS 정국과 대기업 회장은 어떻게 당했나…수감·입대자 노린 중국 해킹 총책 구속 송치",
    "link": "https://www.khan.co.kr/article/202605211200011",
    "pubDate": "Thu, 21 May 2026 03:00:00 GMT",
    "source": "경향신문",
    "domain": "khan.co.kr",
    "thumb": "https://img.khan.co.kr/news/2026/05/21/news-p.v1.20250614.b4be3c509ff6472baed7a655503d7c5c_P1.jpg"
  },
  {
    "title": "BTS, 25일 美 ‘아메리칸 뮤직 어워즈’ 특별 출연",
    "link": "https://www.chosun.com/culture-life/culture_general/2026/05/21/AWLQ4XE2SJB3HG3O2SCTYN7XBQ/",
    "pubDate": "Thu, 21 May 2026 02:09:22 GMT",
    "source": "조선일보",
    "domain": "chosun.com",
    "thumb": "https://www.chosun.com/resizer/v2/G4ZGCZTFGNRWEMRVHE4WIZRWG4.jpg?auth=93c0c18866a6681a419582ed04336bab358af4fdc4f525c0ae817eda6da740db&amp;width=1200&amp;height=630&amp;smart=true"
  },
  {
    "title": "BTS 뷔 '크리스마스 트리', 스포티파이 5억 스트리밍",
    "link": "https://v.daum.net/v/20260519171556657",
    "pubDate": "Tue, 19 May 2026 08:15:56 GMT",
    "source": "v.daum.net",
    "domain": "v.daum.net",
    "thumb": "https://img1.daumcdn.net/thumb/S1200x630/?fname=https://t1.daumcdn.net/news/202605/19/yonhap/20260519171556239vjiz.jpg"
  },
  {
    "title": "BTS 컴백, 공연 넘어 '도시 이벤트' 됐다",
    "link": "https://www.yna.co.kr/view/AKR20260519051400017",
    "pubDate": "Tue, 19 May 2026 01:07:31 GMT",
    "source": "연합뉴스",
    "domain": "yna.co.kr",
    "thumb": "https://img2.yna.co.kr/etc/inner/KR/2026/05/19/AKR20260519051400017_01_i_P4.jpg"
  }
]