[
  {
    "title": "'전액 현금' 장원영·뷔→'방배 청약' 안유진, 넘사벽 영앤리치 클래스 [스타이슈]",
    "link": "https://v.daum.net/v/20260712060209188",
    "pubDate": "Sat, 11 Jul 2026 21:02:09 GMT",
    "source": "v.daum.net",
    "domain": "v.daum.net",
    "thumb": "https://img1.daumcdn.net/thumb/S1200x630/?fname=https://t1.daumcdn.net/news/202607/12/starnews/20260712060211481cxvn.jpg"
  },
  {
    "title": "\"이렇게 컸어?\" 추사랑, 장원영 옆에서도 빛난 폭풍 성장",
    "link": "https://news.nate.com/view/20260711n08967",
    "pubDate": "Sat, 11 Jul 2026 07:58:00 GMT",
    "source": "네이트",
    "domain": "news.nate.com",
    "thumb": "https://thumbnews.nateimg.co.kr/view610///news.nateimg.co.kr/orgImg/nn/2026/07/11/202607111656522410_1.jpg"
  },
  {
    "title": "야노 시호, 딸 추사랑+장원영-누가 제일 예쁠까?",
    "link": "https://www.mediafine.co.kr/news/articleView.html?idxno=83258",
    "pubDate": "Sat, 11 Jul 2026 05:40:35 GMT",
    "source": "미디어파인",
    "domain": "mediafine.co.kr",
    "thumb": "https://cdn.mediafine.co.kr/news/photo/202607/83258_120282_4031.jpeg"
  },
  {
    "title": "14세' 추사랑, 173cm 장원영 옆에서도 안 밀리네…폭풍성장 비율",
    "link": "https://v.daum.net/v/20260711134051799",
    "pubDate": "Sat, 11 Jul 2026 04:40:51 GMT",
    "source": "v.daum.net",
    "domain": "v.daum.net",
    "thumb": "https://img1.daumcdn.net/thumb/S1200x630/?fname=https://t1.daumcdn.net/news/202607/11/mydaily/20260711134053717mvuz.jpg"
  },
  {
    "title": "장원영이 픽한 제2의 라부부? 용산에 ‘와쿠쿠’ 우르르 [언박싱]",
    "link": "https://biz.heraldcorp.com/article/10804656",
    "pubDate": "Sat, 11 Jul 2026 03:15:00 GMT",
    "source": "헤럴드경제",
    "domain": "biz.heraldcorp.com",
    "thumb": "https://wimg.heraldcorp.com/news/cms/2026/07/10/news-p.v1.20260710.2353b8104f524426b0f2d515fe196049_T1.jpeg"
  },
  {
    "title": "안유진은 방배 청약 당첨, 장원영은 137억 한남동 집…영앤리치 아이브",
    "link": "https://news.nate.com/view/20260711n05682",
    "pubDate": "Sat, 11 Jul 2026 03:05:00 GMT",
    "source": "네이트",
    "domain": "news.nate.com",
    "thumb": "https://thumbnews.nateimg.co.kr/view610///news.nateimg.co.kr/orgImg/hm/2026/07/11/news-p.v1.20260711.d51ccad260da46b9b1fa2cc6f3f87764_P1.png"
  },
  {
    "title": "'사춘기' 추사랑, 장원영 옆에서도 '폭풍성장'…모델 DNA 통했다",
    "link": "https://news.nate.com/view/20260711n04590",
    "pubDate": "Sat, 11 Jul 2026 01:31:00 GMT",
    "source": "네이트",
    "domain": "news.nate.com",
    "thumb": "https://thumbnews.nateimg.co.kr/view610///news.nateimg.co.kr/orgImg/aa/2026/07/11/news-p.v1.20260711.1a3920019e7b4917a8de3835c8708fd5_P1.png"
  },
  {
    "title": "'137억 빌라' 장원영 이어…안유진, 40억 아파트 당첨됐나",
    "link": "https://www.hankyung.com/article/202607108515H",
    "pubDate": "Fri, 10 Jul 2026 10:15:01 GMT",
    "source": "한국경제",
    "domain": "hankyung.com",
    "thumb": "https://img.hankyung.com/photo/202607/01.44989371.1.jpg"
  },
  {
    "title": "'137억 빌라' 장원영 이어…안유진, 방배 청약 당첨 '시세차익 18억' 기대 [엑's 이슈]",
    "link": "https://www.xportsnews.com/article/2170445",
    "pubDate": "Fri, 10 Jul 2026 08:03:34 GMT",
    "source": "xportsnews.com",
    "domain": "xportsnews.com",
    "thumb": "https://image.xportsnews.com/contents/images/upload/article/2026/0710/1783670039832761.webp"
  },
  {
    "title": "라이즈 성찬, 공항서 사생팬에 팔꿈치 대응…“장원영 때와 다르네” 갑론을박",
    "link": "https://sports.khan.co.kr/article/202607101048003",
    "pubDate": "Fri, 10 Jul 2026 01:48:00 GMT",
    "source": "스포츠경향",
    "domain": "sports.khan.co.kr",
    "thumb": null
  },
  {
    "title": "\"팔등신 마네킹인줄\"…장원영, 윙크 한 번에 스튜디오 마비",
    "link": "https://v.daum.net/v/FUehwRIkEB",
    "pubDate": "Thu, 09 Jul 2026 21:16:49 GMT",
    "source": "v.daum.net",
    "domain": "v.daum.net",
    "thumb": "https://img1.daumcdn.net/thumb/S1200x630/?fname=https://t1.daumcdn.net/news/202607/10/mydaily/20260710061651645zuna.jpg"
  },
  {
    "title": "네일도 ‘꾸안꾸’가 대세? 신민아 · 장원영이 띄운 ‘클린 네일’",
    "link": "https://www.ledesk.co.kr/view.php?uid=16190",
    "pubDate": "Thu, 09 Jul 2026 04:41:00 GMT",
    "source": "르데스크",
    "domain": "ledesk.co.kr",
    "thumb": "https://img.ledesk.co.kr/titleimg/2026/16190_file_1.webp"
  },
  {
    "title": "신민아, 김민하, 장원영, 레이 손톱으로 보는 네일 트렌드 4",
    "link": "https://www.cosmopolitan.co.kr/article/1905947",
    "pubDate": "Thu, 09 Jul 2026 03:18:32 GMT",
    "source": "cosmopolitan.co.kr",
    "domain": "cosmopolitan.co.kr",
    "thumb": "https://www.cosmopolitan.co.kr/resources/online/thumbnail/hf/2026/07/09/b9f291e2-cc74-4f25-bd9e-e917c24278ad.jpg"
  },
  {
    "title": "‘장원영 렌즈’ 하파크리스틴, 사모펀드에 매각 ‘눈앞’…본계약 체결",
    "link": "https://biz.heraldcorp.com/article/10803620",
    "pubDate": "Thu, 09 Jul 2026 03:03:01 GMT",
    "source": "헤럴드경제",
    "domain": "biz.heraldcorp.com",
    "thumb": "https://wimg.heraldcorp.com/news/cms/2026/07/09/news-p.v1.20260709.dc5af55c30754374899a34417d9fc86e_T1.png"
  },
  {
    "title": "아이브 장원영, 한여름에 청청 패션도 시원하게 소화…비결은 한 줌 허리 - 조선비즈",
    "link": "https://biz.chosun.com/entertainment/enter_general/2026/07/08/MUZDMMLBGJRWCOBVMQYWMODBMU/",
    "pubDate": "Wed, 08 Jul 2026 00:38:00 GMT",
    "source": "Chosunbiz",
    "domain": "biz.chosun.com",
    "thumb": "https://biz.chosun.com/resizer/v2/GA4TSM3FHA4DONLFHE4DEMZQMU.jpg?auth=973d0ab69efb61806067e9d11fc28dcfca1b4dc30fe87243437cd11b7a491415&amp;width=900&amp;height=472&amp;smart=true"
  },
  {
    "title": "장원영, 크롭티 속 복근 '눈길'…힙한 분위기도 찰떡인 미모 [N샷]",
    "link": "https://v.daum.net/v/20260708082234629",
    "pubDate": "Tue, 07 Jul 2026 23:22:34 GMT",
    "source": "v.daum.net",
    "domain": "v.daum.net",
    "thumb": "https://img1.daumcdn.net/thumb/S1200x630/?fname=https://t1.daumcdn.net/news/202607/08/NEWS1/20260708082236570psnc.jpg"
  },
  {
    "title": "장원영, 대단한 N년째 '11자 복근' 지킴이..\"아름답다고 말하다 지쳤다\"",
    "link": "https://www.starnewskorea.com/music/2026/07/07/2026070719532379436",
    "pubDate": "Tue, 07 Jul 2026 11:09:37 GMT",
    "source": "starnewskorea.com",
    "domain": "starnewskorea.com",
    "thumb": "https://image.starnewskorea.com/cdn-cgi/image/f=auto,w=1200,h=1029,fit=cover,q=high,sharpen=2/21/2026/07/2026070719532379436_1.jpg"
  },
  {
    "title": "장원영, 데님 스타일로 근황…‘REVIVE+’ 활동 잇는 일상",
    "link": "https://www.topstarnews.net/news/articleView.html?idxno=16126897",
    "pubDate": "Tue, 07 Jul 2026 10:35:26 GMT",
    "source": "톱스타뉴스",
    "domain": "topstarnews.net",
    "thumb": "https://cdn.topstarnews.net/news/photo/202607/16126897_1956938_3516_crop.jpg"
  },
  {
    "title": "'장원영 디바이스' 625% 논란의 전말…\"우연일 뿐\" 항변",
    "link": "https://www.hankyung.com/article/202607070105i",
    "pubDate": "Tue, 07 Jul 2026 03:09:59 GMT",
    "source": "한국경제",
    "domain": "hankyung.com",
    "thumb": "https://img.hankyung.com/photo/202607/01.44673039.1.jpg"
  },
  {
    "title": "장원영, 얼굴이 다 했다…초근접 셀카도 ‘굴욕 無’ [DA★]",
    "link": "https://sports.donga.com/ent/article/all/20260703/134234552/1",
    "pubDate": "Fri, 03 Jul 2026 13:00:00 GMT",
    "source": "스포츠동아",
    "domain": "sports.donga.com",
    "thumb": "https://dimg.donga.com/wps/SPORTS/IMAGE/2026/07/03/134234550.1.jpg"
  },
  {
    "title": "장원영, 모자·마스크 벗고 180도 달라졌는데…외모품평·억측까지 '몸살' [엑's 이슈]",
    "link": "https://v.daum.net/v/tQLKVk5T5m",
    "pubDate": "Fri, 03 Jul 2026 09:11:17 GMT",
    "source": "v.daum.net",
    "domain": "v.daum.net",
    "thumb": "https://img1.daumcdn.net/thumb/S1200x630/?fname=https://t1.daumcdn.net/news/202607/03/xportsnews/20260703181119344empo.jpg"
  },
  {
    "title": "장원영, 특혜 논란에 모자 벗었더니…이번엔 민낯 품평 쏟아졌다",
    "link": "https://sports.khan.co.kr/article/202607021622003",
    "pubDate": "Thu, 02 Jul 2026 07:00:00 GMT",
    "source": "스포츠경향",
    "domain": "sports.khan.co.kr",
    "thumb": null
  },
  {
    "title": "\"멤버들 다 가렸는데\"...장원영, '특혜 논란' 의식했나 '맨얼굴'로 공항 등장",
    "link": "https://v.daum.net/v/20260625042141043",
    "pubDate": "Thu, 25 Jun 2026 07:00:00 GMT",
    "source": "v.daum.net",
    "domain": "v.daum.net",
    "thumb": "https://img1.daumcdn.net/thumb/S1200x630/?fname=https://t1.daumcdn.net/news/202606/25/fnnewsi/20260625042142029rhbb.jpg"
  },
  {
    "title": "공항 신원 확인 논란…장원영, 이번엔 맨얼굴로 등장",
    "link": "https://v.daum.net/v/20260624144146421",
    "pubDate": "Wed, 24 Jun 2026 07:00:00 GMT",
    "source": "v.daum.net",
    "domain": "v.daum.net",
    "thumb": "https://img1.daumcdn.net/thumb/S1200x630/?fname=https://t1.daumcdn.net/news/202606/24/segye/20260624144146848oqtu.jpg"
  },
  {
    "title": "공항 태도 논란 의식했나?…장원영, 모자·마스크 없이 출국",
    "link": "https://www.ytn.co.kr/_ln/0117_202606241033143538",
    "pubDate": "Wed, 24 Jun 2026 07:00:00 GMT",
    "source": "YTN",
    "domain": "ytn.co.kr",
    "thumb": "https://image.ytn.co.kr/general/jpg/2026/0624/202606241033143538_t.jpg"
  },
  {
    "title": "‘특혜 논란’ 장원영, 공항서 마스크·모자 벗고 신원확인",
    "link": "https://v.daum.net/v/20260624124353948",
    "pubDate": "Wed, 24 Jun 2026 07:00:00 GMT",
    "source": "v.daum.net",
    "domain": "v.daum.net",
    "thumb": "https://img1.daumcdn.net/thumb/S1200x630/?fname=https://t1.daumcdn.net/news/202606/24/ned/20260624124353497zfqb.png"
  },
  {
    "title": "안내까지 바꾼 장원영, 홀로 ‘맨얼굴’로 공항 등장",
    "link": "https://v.daum.net/v/20260623172016243",
    "pubDate": "Tue, 23 Jun 2026 07:00:00 GMT",
    "source": "v.daum.net",
    "domain": "v.daum.net",
    "thumb": "https://img1.daumcdn.net/thumb/S1200x630/?fname=https://t1.daumcdn.net/news/202606/23/sportskhan/20260623172018202dzpg.jpg"
  },
  {
    "title": "장원영·카리나처럼 입어볼까…양말 보일수록 ‘힙하다’는 요즘 패션 [트렌드]",
    "link": "https://v.daum.net/v/8CT7hTFYNq",
    "pubDate": "Tue, 23 Jun 2026 07:00:00 GMT",
    "source": "v.daum.net",
    "domain": "v.daum.net",
    "thumb": "https://img1.daumcdn.net/thumb/S1200x630/?fname=https://t1.daumcdn.net/news/202606/23/segye/20260623052436545xqhd.jpg"
  },
  {
    "title": "장원영, 논란 이후 달라져… \"모자 벗으며 방긋 웃어\"",
    "link": "https://v.daum.net/v/20260623214423741",
    "pubDate": "Tue, 23 Jun 2026 07:00:00 GMT",
    "source": "v.daum.net",
    "domain": "v.daum.net",
    "thumb": "https://img1.daumcdn.net/thumb/S1200x630/?fname=https://t1.daumcdn.net/news/202606/23/mydaily/20260623214423553gtfs.jpg"
  },
  {
    "title": "생얼 굴욕 無 장원영, 선상 위 압도적 뒤태…21세 영앤리치의 삶",
    "link": "https://v.daum.net/v/KXCDdfJ6zn",
    "pubDate": "Sun, 21 Jun 2026 07:00:00 GMT",
    "source": "v.daum.net",
    "domain": "v.daum.net",
    "thumb": "https://img1.daumcdn.net/thumb/S1200x630/?fname=https://t1.daumcdn.net/news/202606/21/sportskhan/20260621153818531dhum.png"
  },
  {
    "title": "결국 ‘장원영이 바꿨다’···“마스크 내려주세요” 명문화",
    "link": "https://sports.khan.co.kr/article/202606201423003",
    "pubDate": "Sat, 20 Jun 2026 07:00:00 GMT",
    "source": "스포츠경향",
    "domain": "sports.khan.co.kr",
    "thumb": null
  },
  {
    "title": "장원영, 악플에 전쟁 선언…스타쉽 \"법적 대응\"",
    "link": "https://www.newsis.com/view/NISX20260618_0003674524",
    "pubDate": "Thu, 18 Jun 2026 07:00:00 GMT",
    "source": "뉴시스",
    "domain": "newsis.com",
    "thumb": "https://img1.newsis.com/2026/04/23/NISI20260423_0021256715_web.jpg"
  },
  {
    "title": "‘출국 태도 논란’ 장원영 소속사 “악플러 강경 대응”",
    "link": "https://www.donga.com/news/Society/article/all/20260618/134137228/2",
    "pubDate": "Thu, 18 Jun 2026 07:00:00 GMT",
    "source": "동아일보",
    "domain": "donga.com",
    "thumb": "https://dimg.donga.com/wps/NEWS/IMAGE/2026/06/18/134137220.3.jpg"
  },
  {
    "title": "장원영 비방 콘텐츠 유포자 추적···소속사 “국제 공조로 끝까지 찾는다”",
    "link": "https://www.khan.co.kr/article/202606181504011",
    "pubDate": "Thu, 18 Jun 2026 07:00:00 GMT",
    "source": "경향신문",
    "domain": "khan.co.kr",
    "thumb": "https://img.khan.co.kr/news/2026/06/18/news-p.v1.20260618.809a22bad2c34ba7a3f7c30d5b88a82b_P1.png"
  },
  {
    "title": "장원영 출국 심사 후폭풍, 결국 안내 방침 바꾼다",
    "link": "https://sports.khan.co.kr/article/202606161146003",
    "pubDate": "Tue, 16 Jun 2026 07:00:00 GMT",
    "source": "스포츠경향",
    "domain": "sports.khan.co.kr",
    "thumb": null
  },
  {
    "title": "'마스크만 살짝' 장원영 출국장 논란에...결국 공항 방침 바꾼다 - 머니투데이",
    "link": "https://www.mt.co.kr/society/2026/06/16/2026061612522995012",
    "pubDate": "Tue, 16 Jun 2026 07:00:00 GMT",
    "source": "머니투데이",
    "domain": "mt.co.kr",
    "thumb": "https://thumb.mt.co.kr/cdn-cgi/image/w=1200,h=922,fit=cover,bg=whilte,f=auto,quality=high,sharpen=2,g=face/21/2026/06/2026061612522995012_2.jpg"
  },
  {
    "title": "마스크 쓴 장원영 공항 신분확인 논란…공항공사 \"절차안내 강화\"",
    "link": "https://www.yna.co.kr/view/AKR20260616151300004",
    "pubDate": "Tue, 16 Jun 2026 07:00:00 GMT",
    "source": "연합뉴스",
    "domain": "yna.co.kr",
    "thumb": "https://img1.yna.co.kr/photo/cms/2025/02/25/72/PCM20250225000072050_P4.jpg"
  },
  {
    "title": "장원영 출국 영상 보더니…“마스크 기준이 뭐죠?” 민원 [잇슈 키워드]",
    "link": "https://news.kbs.co.kr/news/view.do?ncd=8587100",
    "pubDate": "Tue, 16 Jun 2026 07:00:00 GMT",
    "source": "KBS 뉴스",
    "domain": "news.kbs.co.kr",
    "thumb": "http://news.kbs.co.kr/data/news/title_image/newsmp4/newsplaza_p1/2026/06/16/320_8587100.jpg"
  },
  {
    "title": "“기준이 뭐냐” 장원영 출국 심사, 민원으로 번졌다",
    "link": "https://sports.khan.co.kr/article/202606151000003",
    "pubDate": "Mon, 15 Jun 2026 07:00:00 GMT",
    "source": "스포츠경향",
    "domain": "sports.khan.co.kr",
    "thumb": null
  },
  {
    "title": "장원영, 공손한 인사 - 스타투데이",
    "link": "https://www.mk.co.kr/news/photos/12071540",
    "pubDate": "Thu, 11 Jun 2026 07:00:00 GMT",
    "source": "매일경제",
    "domain": "mk.co.kr",
    "thumb": "https://pimg.mk.co.kr/news/cms/202606/11/news-p.v1.20260611.226f11b7d4a249f69e6728e6780d61ed_R.jpg"
  }
]